{
  "rspCode": "0",
  "rspMsg": "success",
  "data": {
    "content": "<h1>法国近况：</h1><p style=\"line-height:20px;text-indent:2em;\"> 法国队阵中拥有格里兹曼、博格巴、坎特和姆巴佩等顶级球星，球队也是本届世界杯的夺冠热门，从小组赛开始，法国队便展现出十足的竞争力，球队轻松获得出线资格后，在淘汰赛中先后将南美劲旅阿根廷和乌拉圭淘汰出局，成功晋级半决赛，从数据上来看，法国队目前的进攻火力十分强劲，球队5场比赛合计轰入9球，进攻端的格里兹曼、姆巴佩等人多点开花，而防守端有坎特、乌姆蒂蒂和瓦拉内这个铁三角组合，法国队的防守也是值得信赖，本场半决赛面对比利时，法国队自然是志在胜利。<img style=\"margin:10px 0;\" src=\"http://static.sporttery.cn/images/2018/07/10/9-1PG00T433D0.jpg\" /></p>",
    "title": "[世界杯]克罗地亚点球大战淘汰丹麦",
    "time": "2018-07-01 13:44",
    "shareImg":"http://static.sporttery.cn/images/2018/07/10/9-1PG00T433D0.jpg"
  }
}